devops_intc/__init__.py
devops_intc/main.py
devops_intc-0.1.15.dist-info/METADATA
devops_intc-0.1.15.dist-info/WHEEL
devops_intc-0.1.15.dist-info/entry_points.txt
devops_intc-0.1.15.dist-info/top_level.txt
devops_intc-0.1.15.dist-info/RECORD
