Metadata-Version: 2.1
Name: devops-intc
Version: 0.1.15
Summary: Testing PyPi
Home-page: UNKNOWN
Author: Emilio Reyes, James Gregg
Author-email: emilio.reyes@intel.com, james.r.gregg@intel.com
License: UNKNOWN
Platform: UNKNOWN
Classifier: Programming Language :: Python :: 3.7
Classifier: Programming Language :: Python :: 3.8
Classifier: Programming Language :: Python :: 3.9
Classifier: Programming Language :: Python :: 3.10
Requires-Python: >=3.7
Requires-Dist: rest3client
